dwell/__init__.py
dwell/caselessdict.py
dwell/climate/__init__.py
dwell/climate/gridding/__init__.py
dwell/constants/__init__.py
dwell/fft/__init__.py
dwell/fft/_internal.py
dwell/io/__init__.py
dwell/io/netcdf.py
dwell/io/netcdf_tools/__init__.py
dwell/io/netcdf_tools/boolfilter.py
dwell/io/netcdf_tools/filter.py
dwell/planck/__init__.py
dwell/rad/__init__.py
dwell/rad/debug_files.py
dwell/rad/deprecated.py
dwell/rad/deprecated_example.py
dwell/rad/log.py
dwell/rad/prompt.py
dwell/rad/terminal.py
dwell/smoothing/__init__.py
dwell/testing/__init__.py
dwell/testing/test_caselessdict.py
dwell/testing/test_planck.py
dwell/testing/test_smoothing.py
dwell-1.0.0a3.dist-info/DESCRIPTION.rst
dwell-1.0.0a3.dist-info/METADATA
dwell-1.0.0a3.dist-info/RECORD
dwell-1.0.0a3.dist-info/WHEEL
dwell-1.0.0a3.dist-info/entry_points.txt
dwell-1.0.0a3.dist-info/metadata.json
dwell-1.0.0a3.dist-info/top_level.txt
