Metadata-Version: 2.0
Name: dwell
Version: 1.0.0a3
Summary: Some Python packages for fft, smoothing, gridding
Home-page: http://christopherlee.co.uk
Author: Christopher Lee
Author-email: lee@aeolisresearch.com
License: BSD
Platform: UNKNOWN
Classifier: Development Status :: 3 - Alpha
Classifier: Programming Language :: Python :: 2.7
Classifier: Programming Language :: Python :: 3
Requires-Dist: argh
Requires-Dist: nose
Requires-Dist: numpy
Requires-Dist: scipy
Requires-Dist: six
Requires-Dist: termcolor
